{
  "version": 1,
  "timestamp": "2026-06-07T14:19:54.171Z",
  "changeType": "bugfix",
  "activity": {
    "activeTimeSeconds": 1251,
    "fileChangeEvents": 108,
    "keystrokes": 0
  },
  "files": {
    "totalChangedFiles": 84,
    "extensions": {
      ".json": 32,
      ".781c76c4b8c041d4": 1,
      ".09a0d4b8402c4acf": 1,
      ".f33afd4c32671f15": 1,
      ".c8ff89f2516c3c41": 1,
      ".7f51ddb2508b2ae4": 1,
      ".e10d418582d0c349": 1,
      ".d22fdfda8cdf2cf3": 1,
      ".4b61c31d232b68da": 1,
      ".1f2be885173046ab": 1,
      ".004965f5aee01c5b": 1,
      ".919ea4f0826f9155": 1,
      ".30a78dbf077bbfba": 1,
      ".4ee389c3f78afb46": 1,
      ".a9bde03b7b0c1928": 1,
      ".cb2311d34e390706": 1,
      ".0168dce86c9d0f83": 1,
      ".cc57ae03c8338476": 1,
      ".8e24c5fe3423db05": 1,
      ".5fc86ee75475c06b": 1,
      ".d23ec22825000f3a": 1,
      ".fd920d896313edcc": 1,
      ".3592a89bbf425714": 1,
      ".e24cb44e8d99cb5c": 1,
      ".0f562b9d923d4295": 1,
      ".2990a0cd0cdaa18c": 1,
      ".6d58559fddc2232d": 1,
      ".97d6c20584198508": 1,
      ".491e3b80d2bbe1bc": 1,
      ".6c4e3779c42619c1": 1,
      ".0b1cafcf174c0459": 1,
      ".5767330b9ede15ec": 1,
      ".abad6f794db31cb0": 1,
      ".0cad1c1f3efe3125": 1,
      ".a74de7bc5c80ba67": 1,
      ".225cd2b815fe777c": 1,
      "unknown": 2,
      ".ff1a1565d208c9c3": 1,
      ".a186b1c4c401e73d": 1,
      ".30536685bc30ba47": 1,
      ".6b898531fe44f4e5": 1,
      ".4ddafbf9da09a913": 1,
      ".788b593d02e03799": 1,
      ".6e73287b33f6d379": 1,
      ".051fee39f4e81126": 1,
      ".b3f7e5cb23351265": 1,
      ".c5fc9ff05c1456a8": 1,
      ".c91c0341d3df311c": 1,
      ".b0597b02606ea3a5": 1,
      ".da2f6d9967e11608": 1,
      ".git": 2
    }
  },
  "workspaceId": "L1VzZXJzL2FsZG8vRG9jdW1lbnRzL3Byb2plY3RzL3RpY2tldF9yaXNl"
}