{
  "version": 1,
  "timestamp": "2026-01-05T07:18:45.150Z",
  "changeType": "bugfix",
  "activity": {
    "activeTimeSeconds": 5484,
    "fileChangeEvents": 205,
    "keystrokes": 0
  },
  "files": {
    "totalChangedFiles": 75,
    "extensions": {
      "unknown": 6,
      ".ts": 1,
      ".git": 4,
      ".yml": 1,
      ".kts": 1,
      ".dart": 2,
      ".h": 3,
      ".cc": 2,
      ".java": 1,
      ".m": 1,
      ".swift": 1,
      ".cmake": 2,
      ".lock": 5,
      ".bin": 7,
      ".properties": 2,
      ".salive": 1,
      ".stamp": 13,
      ".dill": 1,
      ".d": 10,
      ".json": 4,
      ".so": 3,
      ".probe": 1,
      ".yaml": 1,
      ".1767597366069": 1,
      ".1767597383715": 1
    }
  },
  "workspaceId": "L1VzZXJzL2FsZG8vRG9jdW1lbnRzL3Byb2plY3RzL3RpY2tldF9yaXNl"
}