{
  "version": 1,
  "timestamp": "2026-05-23T07:22:18.215Z",
  "changeType": "bugfix",
  "activity": {
    "activeTimeSeconds": 237,
    "fileChangeEvents": 30,
    "keystrokes": 0
  },
  "files": {
    "totalChangedFiles": 24,
    "extensions": {
      ".py": 2,
      ".281473701231872": 1,
      ".pyc": 2,
      "unknown": 1,
      ".json": 8,
      ".bced86fa45f2d06d": 1,
      ".281472243195936": 1,
      ".36d9f0c5141a10dd": 1,
      ".4139e5581d1e4e28": 1,
      ".ed3c6f34230b90b6": 1,
      ".edc8b8ff77ffafa8": 1,
      ".42677e123111cb67": 1,
      ".0345d1489d53799e": 1,
      ".04c87241972658e5": 1,
      ".ae446e884bda17fc": 1
    }
  },
  "workspaceId": "L1VzZXJzL2FsZG8vRG9jdW1lbnRzL3Byb2plY3RzL21lZXRpbmdfbm90ZQ__"
}