{
  "version": 1,
  "timestamp": "2026-06-07T20:20:52.851Z",
  "changeType": "bugfix",
  "activity": {
    "activeTimeSeconds": 3889,
    "fileChangeEvents": 96,
    "keystrokes": 396073
  },
  "files": {
    "totalChangedFiles": 38,
    "extensions": {
      ".json": 4,
      ".98326fd3f48f": 1,
      ".dbddc740eea3": 1,
      ".lock": 12,
      ".bin": 4,
      ".217c9b057893": 1,
      "unknown": 3,
      ".a0751a4f89f0": 1,
      ".png": 4,
      ".80a0451c1281": 1,
      ".dart": 2,
      ".6b8e0ff18c6e": 1,
      ".6476f61ab509": 1,
      ".yaml": 1,
      ".ac01ffbb987d": 1
    }
  },
  "workspaceId": "L1VzZXJzL2FsZG8vRG9jdW1lbnRzL3Byb2plY3RzL3RpY2tldF9yaXNl"
}