{
  "version": 1,
  "timestamp": "2026-01-31T23:48:59.600Z",
  "changeType": "bugfix",
  "activity": {
    "activeTimeSeconds": 995,
    "fileChangeEvents": 101,
    "keystrokes": 0
  },
  "files": {
    "totalChangedFiles": 15,
    "extensions": {
      ".ts": 2,
      "unknown": 1,
      ".path]]": 1,
      ".py": 3,
      ".git": 3,
      ".yml": 2,
      ".yaml": 1,
      ".json": 1,
      ".f435eb607eaf9462": 1
    }
  },
  "workspaceId": "L1VzZXJzL2FsZG8vRG9jdW1lbnRzL3Byb2plY3RzL3RpY2tldF9yaXNl"
}