{
  "version": 1,
  "timestamp": "2026-03-31T08:09:11.557Z",
  "changeType": "docs",
  "activity": {
    "activeTimeSeconds": 228,
    "fileChangeEvents": 33,
    "keystrokes": 0
  },
  "files": {
    "totalChangedFiles": 32,
    "extensions": {
      ".473f2cd6f94e0cfe": 1,
      ".json": 15,
      ".0ef9e03f4e9c1ebe": 1,
      ".05d48e7894c4839b": 1,
      ".4a83f8d06fa37ce3": 1,
      ".f4108c9e3077653c": 1,
      ".2cf58694dfbda88b": 1,
      ".a47dd60068de72ed": 1,
      ".748666689d230849": 1,
      ".7ea1d88d88f4168a": 1,
      ".c57c083b87680707": 1,
      ".ae567cc290a4ce77": 1,
      ".ebbd1357ccfcdaf7": 1,
      ".132ea5aa3f3da6ba": 1,
      ".471165893a98a33f": 1,
      ".53dcb37f693f5b67": 1,
      ".fba7cc202b0eb93c": 1,
      ".b390bd9bbca2b2fb": 1
    }
  },
  "workspaceId": "L1VzZXJzL2FsZG8vRG9jdW1lbnRzL3Byb2plY3RzL3RpY2tldF9yaXNl"
}